biobalm/__init__.py
biobalm/control.py
biobalm/drivers.py
biobalm/interaction_graph_utils.py
biobalm/motif_avoidant.py
biobalm/petri_net_translation.py
biobalm/space_utils.py
biobalm/succession_diagram.py
biobalm/symbolic_utils.py
biobalm/trappist_core.py
biobalm/types.py
biobalm/_sd_algorithms/__init__.py
biobalm/_sd_algorithms/compute_attractor_seeds.py
biobalm/_sd_algorithms/expand_attractor_seeds.py
biobalm/_sd_algorithms/expand_bfs.py
biobalm/_sd_algorithms/expand_dfs.py
biobalm/_sd_algorithms/expand_minimal_spaces.py
biobalm/_sd_algorithms/expand_source_SCCs.py
biobalm/_sd_algorithms/expand_to_target.py
biobiobalm-0.0.0.dist-info/LICENSE
biobiobalm-0.0.0.dist-info/METADATA
biobiobalm-0.0.0.dist-info/WHEEL
biobiobalm-0.0.0.dist-info/top_level.txt
biobiobalm-0.0.0.dist-info/RECORD
