Metadata-Version: 2.1
Name: biobiobalm
Version: 0.0.0
Summary: Boolean Attractor Landscape Mapper
Author-email: Jordan Rozum <jrozum@binghamton.edu>
Requires-Python: >=3.11
License-File: LICENSE
Requires-Dist: biodivine-aeon ==1.0.0a4
Requires-Dist: clingo >=5.6.2
Requires-Dist: networkx >=2.8.8
Requires-Dist: pypint >=1.6.2
